symtest/__init__.py
symtest/__main__.py
symtest/byte2op.py
symtest/sevm.py
symtest/utils.py
symtest-0.0.0.11.dist-info/LICENSE
symtest-0.0.0.11.dist-info/METADATA
symtest-0.0.0.11.dist-info/WHEEL
symtest-0.0.0.11.dist-info/entry_points.txt
symtest-0.0.0.11.dist-info/top_level.txt
symtest-0.0.0.11.dist-info/RECORD
