Metadata-Version: 2.1
Name: symtest
Version: 0.0.0.11
Summary: SymTest: Symbolic Bounded Model Checker for Ethereum Smart Contracts Bytecode
Author: Daejun Park
Project-URL: Homepage, https://github.com/a16z/symtest
Classifier: Programming Language :: Python :: 3
Classifier: License :: OSI Approved :: GNU Affero General Public License v3
Classifier: Operating System :: OS Independent
Requires-Python: >=3.6
License-File: LICENSE
Requires-Dist: crytic-compile (>=0.3.0)
Requires-Dist: z3-solver
